{
  "extraction_time": "2025-12-05T14:59:34.738267",
  "stage": "semantic_extraction",
  "stats": {
    "items_processed": 6,
    "entities": 32,
    "relations": 12,
    "errors": 20
  },
  "entities": [
    {
      "id": "1",
      "type": "QUY_DINH",
      "text": "Quy chế Đào tạo theo học chế tín chỉ",
      "normalized": "Quy chế Đào tạo theo học chế tín chỉ",
      "confidence": 1.0,
      "source_article_id": "dieu_1",
      "metadata": {
        "article_title": "Điều 1. Cập nhật Quy chế Đào tạo theo học chế tín chỉ"
      }
    },
    {
      "id": "2",
      "type": "QUY_DINH",
      "text": "Quyết định số 790/QĐ-ĐHCNTT",
      "normalized": "Quyết định số 790/QĐ-ĐHCNTT",
      "confidence": 1.0,
      "source_article_id": "dieu_1",
      "metadata": {
        "article_title": "Điều 1. Cập nhật Quy chế Đào tạo theo học chế tín chỉ"
      }
    },
    {
      "id": "3",
      "type": "KY_HOC",
      "text": "học kỳ hè",
      "normalized": "học kỳ hè",
      "confidence": 1.0,
      "source_article_id": "dieu_1",
      "metadata": {
        "article_title": "Điều 1. Cập nhật Quy chế Đào tạo theo học chế tín chỉ"
      }
    },
    {
      "id": "4",
      "type": "HOC_PHI",
      "text": "HPTCHM HKHE",
      "normalized": "HPTCHM HKHE",
      "confidence": 1.0,
      "source_article_id": "dieu_1",
      "metadata": {
        "article_title": "Điều 1. Cập nhật Quy chế Đào tạo theo học chế tín chỉ"
      }
    },
    {
      "id": "5",
      "type": "HOC_PHI",
      "text": "HPTCHM học kỳ hè",
      "normalized": "HPTCHM học kỳ hè",
      "confidence": 1.0,
      "source_article_id": "dieu_1",
      "metadata": {
        "article_title": "Điều 1. Cập nhật Quy chế Đào tạo theo học chế tín chỉ"
      }
    },
    {
      "id": "6",
      "type": "HOC_PHI",
      "text": "HPTCHM học kỳ chính",
      "normalized": "HPTCHM học kỳ chính",
      "confidence": 1.0,
      "source_article_id": "dieu_1",
      "metadata": {
        "article_title": "Điều 1. Cập nhật Quy chế Đào tạo theo học chế tín chỉ"
      }
    },
    {
      "id": "7",
      "type": "HOC_PHI",
      "text": "HPTCHL",
      "normalized": "HPTCHL",
      "confidence": 1.0,
      "source_article_id": "dieu_1",
      "metadata": {
        "article_title": "Điều 1. Cập nhật Quy chế Đào tạo theo học chế tín chỉ"
      }
    },
    {
      "id": "8",
      "type": "HOC_PHI",
      "text": "HPTCCT",
      "normalized": "HPTCCT",
      "confidence": 1.0,
      "source_article_id": "dieu_1",
      "metadata": {
        "article_title": "Điều 1. Cập nhật Quy chế Đào tạo theo học chế tín chỉ"
      }
    },
    {
      "id": "9",
      "type": "SINH_VIEN",
      "text": "sinh viên",
      "normalized": "sinh viên",
      "confidence": 1.0,
      "source_article_id": "dieu_1",
      "metadata": {
        "article_title": "Điều 1. Cập nhật Quy chế Đào tạo theo học chế tín chỉ"
      }
    },
    {
      "id": "10",
      "type": "THOI_GIAN",
      "text": "thời gian học theo thiết kế chương trình đào tạo",
      "normalized": "thời gian học theo thiết kế chương trình đào tạo",
      "confidence": 1.0,
      "source_article_id": "dieu_1",
      "metadata": {
        "article_title": "Điều 1. Cập nhật Quy chế Đào tạo theo học chế tín chỉ"
      }
    },
    {
      "id": "11",
      "type": "HOC_PHI",
      "text": "quy định học phí hiện hành",
      "normalized": "quy định học phí hiện hành",
      "confidence": 1.0,
      "source_article_id": "dieu_1",
      "metadata": {
        "article_title": "Điều 1. Cập nhật Quy chế Đào tạo theo học chế tín chỉ"
      }
    },
    {
      "id": "1",
      "type": "QUY_DINH",
      "text": "Quyết định này",
      "normalized": "Quyết định này",
      "confidence": 1.0,
      "source_article_id": "dieu_2",
      "metadata": {
        "article_title": "Điều 2. Trách nhiệm thi hành"
      }
    },
    {
      "id": "2",
      "type": "KHOA",
      "text": "Phòng, Ban, Khoa, Bộ môn, đơn vị",
      "normalized": "Phòng, Ban, Khoa, Bộ môn, đơn vị",
      "confidence": 1.0,
      "source_article_id": "dieu_2",
      "metadata": {
        "article_title": "Điều 2. Trách nhiệm thi hành"
      }
    },
    {
      "id": "3",
      "type": "SINH_VIEN",
      "text": "sinh viên chính quy",
      "normalized": "sinh viên chính quy",
      "confidence": 1.0,
      "source_article_id": "dieu_2",
      "metadata": {
        "article_title": "Điều 2. Trách nhiệm thi hành"
      }
    },
    {
      "id": "4",
      "type": "THOI_GIAN",
      "text": "ngày ký",
      "normalized": "ngày ký",
      "confidence": 1.0,
      "source_article_id": "dieu_2",
      "metadata": {
        "article_title": "Điều 2. Trách nhiệm thi hành"
      }
    },
    {
      "id": "1",
      "type": "KY_HOC",
      "text": "học kỳ hè",
      "normalized": "học kỳ hè",
      "confidence": 1.0,
      "source_article_id": "khoan_1_dieu_1",
      "metadata": {
        "article_title": "Khoản 1 Điều 1"
      }
    },
    {
      "id": "2",
      "type": "HOC_PHI",
      "text": "HPTCHM HKHE",
      "normalized": "HPTCHM HKHE",
      "confidence": 1.0,
      "source_article_id": "khoan_1_dieu_1",
      "metadata": {
        "article_title": "Khoản 1 Điều 1"
      }
    },
    {
      "id": "3",
      "type": "HOC_PHI",
      "text": "HPTCHM",
      "normalized": "HPTCHM",
      "confidence": 1.0,
      "source_article_id": "khoan_1_dieu_1",
      "metadata": {
        "article_title": "Khoản 1 Điều 1"
      }
    },
    {
      "id": "4",
      "type": "HOC_PHI",
      "text": "HPTCHL",
      "normalized": "HPTCHL",
      "confidence": 1.0,
      "source_article_id": "khoan_1_dieu_1",
      "metadata": {
        "article_title": "Khoản 1 Điều 1"
      }
    },
    {
      "id": "5",
      "type": "HOC_PHI",
      "text": "HPTCCT",
      "normalized": "HPTCCT",
      "confidence": 1.0,
      "source_article_id": "khoan_1_dieu_1",
      "metadata": {
        "article_title": "Khoản 1 Điều 1"
      }
    },
    {
      "id": "6",
      "type": "TIN_CHI",
      "text": "TCHPHM",
      "normalized": "TCHPHM",
      "confidence": 1.0,
      "source_article_id": "khoan_1_dieu_1",
      "metadata": {
        "article_title": "Khoản 1 Điều 1"
      }
    },
    {
      "id": "7",
      "type": "TIN_CHI",
      "text": "TCHPHL",
      "normalized": "TCHPHL",
      "confidence": 1.0,
      "source_article_id": "khoan_1_dieu_1",
      "metadata": {
        "article_title": "Khoản 1 Điều 1"
      }
    },
    {
      "id": "8",
      "type": "TIN_CHI",
      "text": "TCHPCT",
      "normalized": "TCHPCT",
      "confidence": 1.0,
      "source_article_id": "khoan_1_dieu_1",
      "metadata": {
        "article_title": "Khoản 1 Điều 1"
      }
    },
    {
      "id": "9",
      "type": "SINH_VIEN",
      "text": "sinh viên",
      "normalized": "sinh viên",
      "confidence": 1.0,
      "source_article_id": "khoan_1_dieu_1",
      "metadata": {
        "article_title": "Khoản 1 Điều 1"
      }
    },
    {
      "id": "10",
      "type": "THOI_GIAN",
      "text": "thời gian học theo thiết kế chương trình đào tạo",
      "normalized": "thời gian học theo thiết kế chương trình đào tạo",
      "confidence": 1.0,
      "source_article_id": "khoan_1_dieu_1",
      "metadata": {
        "article_title": "Khoản 1 Điều 1"
      }
    },
    {
      "id": "11",
      "type": "QUY_DINH",
      "text": "quy định học phí hiện hành",
      "normalized": "quy định học phí hiện hành",
      "confidence": 1.0,
      "source_article_id": "khoan_1_dieu_1",
      "metadata": {
        "article_title": "Khoản 1 Điều 1"
      }
    },
    {
      "id": "1",
      "type": "SINH_VIEN",
      "text": "sinh viên",
      "normalized": "sinh viên",
      "confidence": 1.0,
      "source_article_id": "khoan_2_dieu_1",
      "metadata": {
        "article_title": "Khoản 2 Điều 12"
      }
    },
    {
      "id": "2",
      "type": "MON_HOC",
      "text": "môn học đại cương",
      "normalized": "môn học đại cương",
      "confidence": 1.0,
      "source_article_id": "khoan_2_dieu_1",
      "metadata": {
        "article_title": "Khoản 2 Điều 12"
      }
    },
    {
      "id": "3",
      "type": "MON_HOC",
      "text": "môn học cơ sở ngành học chung",
      "normalized": "môn học cơ sở ngành học chung",
      "confidence": 1.0,
      "source_article_id": "khoan_2_dieu_1",
      "metadata": {
        "article_title": "Khoản 2 Điều 12"
      }
    },
    {
      "id": "4",
      "type": "DIEU_KIEN",
      "text": "tối thiểu 70 sinh viên",
      "normalized": "tối thiểu 70 sinh viên",
      "confidence": 1.0,
      "source_article_id": "khoan_2_dieu_1",
      "metadata": {
        "article_title": "Khoản 2 Điều 12"
      }
    },
    {
      "id": "5",
      "type": "QUY_DINH",
      "text": "Điều 12",
      "normalized": "Điều 12",
      "confidence": 1.0,
      "source_article_id": "khoan_2_dieu_1",
      "metadata": {
        "article_title": "Khoản 2 Điều 12"
      }
    },
    {
      "id": "6",
      "type": "KHOA",
      "text": "Trường",
      "normalized": "Trường",
      "confidence": 1.0,
      "source_article_id": "khoan_2_dieu_1",
      "metadata": {
        "article_title": "Khoản 2 Điều 12"
      }
    }
  ],
  "relations": [
    {
      "source_id": "3",
      "target_id": "4",
      "type": "QUY_DINH_DIEU_KIEN",
      "confidence": 1.0,
      "evidence": "Đối với học kỳ hè: Học phí = HPTCHM HKHE × TCHPHM + HPTCHL × TCHPHL + HPTCCT × TCHPCT",
      "source_article_id": "dieu_1"
    },
    {
      "source_id": "9",
      "target_id": "10",
      "type": "YEU_CAU",
      "confidence": 1.0,
      "evidence": "Với sinh viên còn trong thời gian học theo thiết kế chương trình đào tạo",
      "source_article_id": "dieu_1"
    },
    {
      "source_id": "9",
      "target_id": "11",
      "type": "YEU_CAU",
      "confidence": 1.0,
      "evidence": "Với sinh viên đã quá thời gian học theo thiết kế chương trình đào tạo: HPTCHM HKHE thực hiện theo quy định học phí hiện hành.",
      "source_article_id": "dieu_1"
    },
    {
      "source_id": "2",
      "target_id": "1",
      "type": "AP_DUNG_CHO",
      "confidence": 1.0,
      "evidence": "Các Ông/Bà Trưởng các Phòng, Ban, Khoa, Bộ môn, đơn vị có liên quan và sinh viên chính quy chịu trách nhiệm thi hành Quyết định này.",
      "source_article_id": "dieu_2"
    },
    {
      "source_id": "3",
      "target_id": "1",
      "type": "AP_DUNG_CHO",
      "confidence": 1.0,
      "evidence": "Các Ông/Bà Trưởng các Phòng, Ban, Khoa, Bộ môn, đơn vị có liên quan và sinh viên chính quy chịu trách nhiệm thi hành Quyết định này.",
      "source_article_id": "dieu_2"
    },
    {
      "source_id": "1",
      "target_id": "2",
      "type": "HOC_TRONG",
      "confidence": 1.0,
      "evidence": "Đối với học kỳ hè: Học phí = HPTCHM HKHE × TCHPHM + HPTCHL × TCHPHL + HPTCCT × TCHPCT",
      "source_article_id": "khoan_1_dieu_1"
    },
    {
      "source_id": "9",
      "target_id": "10",
      "type": "YEU_CAU",
      "confidence": 1.0,
      "evidence": "Với sinh viên còn trong thời gian học theo thiết kế chương trình đào tạo",
      "source_article_id": "khoan_1_dieu_1"
    },
    {
      "source_id": "9",
      "target_id": "11",
      "type": "AP_DUNG_CHO",
      "confidence": 1.0,
      "evidence": "HPTCHM HKHE thực hiện theo quy định học phí hiện hành.",
      "source_article_id": "khoan_1_dieu_1"
    },
    {
      "source_id": "4",
      "target_id": "1",
      "type": "YEU_CAU",
      "confidence": 1.0,
      "evidence": "số lượng sinh viên đăng ký tối thiểu là 70 sinh viên",
      "source_article_id": "khoan_2_dieu_1"
    },
    {
      "source_id": "2",
      "target_id": "5",
      "type": "AP_DUNG_CHO",
      "confidence": 1.0,
      "evidence": "đối với các môn học đại cương",
      "source_article_id": "khoan_2_dieu_1"
    },
    {
      "source_id": "3",
      "target_id": "5",
      "type": "AP_DUNG_CHO",
      "confidence": 1.0,
      "evidence": "đối với các môn học cơ sở ngành học chung toàn Trường",
      "source_article_id": "khoan_2_dieu_1"
    },
    {
      "source_id": "5",
      "target_id": "6",
      "type": "THUOC_KHOA",
      "confidence": 1.0,
      "evidence": "toàn Trường",
      "source_article_id": "khoan_2_dieu_1"
    }
  ],
  "errors": [
    "Failed to parse entity: 1 validation error for SemanticNode\nid\n  Input should be a valid string [type=string_type, input_value=1, input_type=int]\n    For further information visit https://errors.pydantic.dev/2.11/v/string_type",
    "Failed to parse entity: 1 validation error for SemanticNode\nid\n  Input should be a valid string [type=string_type, input_value=2, input_type=int]\n    For further information visit https://errors.pydantic.dev/2.11/v/string_type",
    "Failed to parse entity: 1 validation error for SemanticNode\nid\n  Input should be a valid string [type=string_type, input_value=3, input_type=int]\n    For further information visit https://errors.pydantic.dev/2.11/v/string_type",
    "Failed to parse entity: 1 validation error for SemanticNode\nid\n  Input should be a valid string [type=string_type, input_value=4, input_type=int]\n    For further information visit https://errors.pydantic.dev/2.11/v/string_type",
    "Failed to parse relation: 2 validation errors for SemanticRelation\nsource_id\n  Input should be a valid string [type=string_type, input_value=1, input_type=int]\n    For further information visit https://errors.pydantic.dev/2.11/v/string_type\ntarget_id\n  Input should be a valid string [type=string_type, input_value=2, input_type=int]\n    For further information visit https://errors.pydantic.dev/2.11/v/string_type",
    "Failed to parse relation: 2 validation errors for SemanticRelation\nsource_id\n  Input should be a valid string [type=string_type, input_value=3, input_type=int]\n    For further information visit https://errors.pydantic.dev/2.11/v/string_type\ntarget_id\n  Input should be a valid string [type=string_type, input_value=1, input_type=int]\n    For further information visit https://errors.pydantic.dev/2.11/v/string_type",
    "Failed to parse relation: 2 validation errors for SemanticRelation\nsource_id\n  Input should be a valid string [type=string_type, input_value=4, input_type=int]\n    For further information visit https://errors.pydantic.dev/2.11/v/string_type\ntarget_id\n  Input should be a valid string [type=string_type, input_value=3, input_type=int]\n    For further information visit https://errors.pydantic.dev/2.11/v/string_type",
    "Failed to parse entity: 1 validation error for SemanticNode\nid\n  Input should be a valid string [type=string_type, input_value=1, input_type=int]\n    For further information visit https://errors.pydantic.dev/2.11/v/string_type",
    "Failed to parse entity: 1 validation error for SemanticNode\nid\n  Input should be a valid string [type=string_type, input_value=2, input_type=int]\n    For further information visit https://errors.pydantic.dev/2.11/v/string_type",
    "Failed to parse entity: 1 validation error for SemanticNode\nid\n  Input should be a valid string [type=string_type, input_value=4, input_type=int]\n    For further information visit https://errors.pydantic.dev/2.11/v/string_type",
    "Failed to parse entity: 1 validation error for SemanticNode\nid\n  Input should be a valid string [type=string_type, input_value=5, input_type=int]\n    For further information visit https://errors.pydantic.dev/2.11/v/string_type",
    "Failed to parse entity: 1 validation error for SemanticNode\nid\n  Input should be a valid string [type=string_type, input_value=6, input_type=int]\n    For further information visit https://errors.pydantic.dev/2.11/v/string_type",
    "Failed to parse entity: 1 validation error for SemanticNode\nid\n  Input should be a valid string [type=string_type, input_value=7, input_type=int]\n    For further information visit https://errors.pydantic.dev/2.11/v/string_type",
    "Failed to parse entity: 1 validation error for SemanticNode\nid\n  Input should be a valid string [type=string_type, input_value=8, input_type=int]\n    For further information visit https://errors.pydantic.dev/2.11/v/string_type",
    "Failed to parse entity: 1 validation error for SemanticNode\nid\n  Input should be a valid string [type=string_type, input_value=9, input_type=int]\n    For further information visit https://errors.pydantic.dev/2.11/v/string_type",
    "Failed to parse relation: 2 validation errors for SemanticRelation\nsource_id\n  Input should be a valid string [type=string_type, input_value=1, input_type=int]\n    For further information visit https://errors.pydantic.dev/2.11/v/string_type\ntarget_id\n  Input should be a valid string [type=string_type, input_value=2, input_type=int]\n    For further information visit https://errors.pydantic.dev/2.11/v/string_type",
    "Failed to parse relation: 2 validation errors for SemanticRelation\nsource_id\n  Input should be a valid string [type=string_type, input_value=2, input_type=int]\n    For further information visit https://errors.pydantic.dev/2.11/v/string_type\ntarget_id\n  Input should be a valid string [type=string_type, input_value=3, input_type=int]\n    For further information visit https://errors.pydantic.dev/2.11/v/string_type",
    "Failed to parse relation: 2 validation errors for SemanticRelation\nsource_id\n  Input should be a valid string [type=string_type, input_value=1, input_type=int]\n    For further information visit https://errors.pydantic.dev/2.11/v/string_type\ntarget_id\n  Input should be a valid string [type=string_type, input_value=4, input_type=int]\n    For further information visit https://errors.pydantic.dev/2.11/v/string_type",
    "Failed to parse relation: 2 validation errors for SemanticRelation\nsource_id\n  Input should be a valid string [type=string_type, input_value=1, input_type=int]\n    For further information visit https://errors.pydantic.dev/2.11/v/string_type\ntarget_id\n  Input should be a valid string [type=string_type, input_value=5, input_type=int]\n    For further information visit https://errors.pydantic.dev/2.11/v/string_type",
    "Failed to parse relation: 2 validation errors for SemanticRelation\nsource_id\n  Input should be a valid string [type=string_type, input_value=2, input_type=int]\n    For further information visit https://errors.pydantic.dev/2.11/v/string_type\ntarget_id\n  Input should be a valid string [type=string_type, input_value=7, input_type=int]\n    For further information visit https://errors.pydantic.dev/2.11/v/string_type"
  ]
}